LICENSE
MANIFEST.in
README.md
setup.cfg
setup.py
sf2_loader/__init__.py
sf2_loader.egg-info/PKG-INFO
sf2_loader.egg-info/SOURCES.txt
sf2_loader.egg-info/dependency_links.txt
sf2_loader.egg-info/requires.txt
sf2_loader.egg-info/top_level.txt
sf2_loader/read_sf2/__init__.py
sf2_loader/read_sf2/fluidsynth.py
sf2_loader/read_sf2/libfluidsynth-3.dll
sf2_loader/read_sf2/libgcc_s_sjlj-1.dll
sf2_loader/read_sf2/libglib-2.0-0.dll
sf2_loader/read_sf2/libgobject-2.0-0.dll
sf2_loader/read_sf2/libgomp-1.dll
sf2_loader/read_sf2/libgthread-2.0-0.dll
sf2_loader/read_sf2/libinstpatch-2.dll
sf2_loader/read_sf2/libinstpatch-2.pdb
sf2_loader/read_sf2/libintl-8.dll
sf2_loader/read_sf2/libsndfile-1.dll
sf2_loader/read_sf2/libstdc++-6.dll
sf2_loader/read_sf2/libwinpthread-1.dll
sf2_loader/read_sf2/read_sf2.py
sf2_loader/read_sf2_32bit/__init__.py
sf2_loader/read_sf2_32bit/fluidsynth.py
sf2_loader/read_sf2_32bit/intl.dll
sf2_loader/read_sf2_32bit/libfluidsynth-3.dll
sf2_loader/read_sf2_32bit/libglib-2.0-0.dll
sf2_loader/read_sf2_32bit/libgobject-2.0-0.dll
sf2_loader/read_sf2_32bit/libgthread-2.0-0.dll
sf2_loader/read_sf2_32bit/libinstpatch-2.dll
sf2_loader/read_sf2_32bit/libinstpatch-2.pdb
sf2_loader/read_sf2_32bit/libsndfile-1.dll
sf2_loader/read_sf2_32bit/read_sf2.py