Metadata-Version: 2.1
Name: sf2-loader
Version: 1.19
Summary: This is an easy-to-use soundfonts loader, player and audio renderer in python
Home-page: https://github.com/Rainbow-Dreamer/sf2_loader
Author: Rainbow-Dreamer
Author-email: 1036889495@qq.com
License: LGPLv2.1
Download-URL: https://github.com/Rainbow-Dreamer/sf2_loader/archive/1.19.tar.gz
Keywords: soundfont,sf2,python
Platform: UNKNOWN
Classifier: Development Status :: 3 - Alpha
Classifier: Intended Audience :: Developers
Classifier: Topic :: Software Development :: Build Tools
Classifier: License :: OSI Approved :: GNU Lesser General Public License v2 or later (LGPLv2+)
Classifier: Programming Language :: Python :: 3.6
Classifier: Programming Language :: Python :: 3.7
Classifier: Programming Language :: Python :: 3.8
Classifier: Programming Language :: Python :: 3.9
Classifier: Programming Language :: Python :: 3.10
